rdflib/__init__.py
rdflib/collection.py
rdflib/compare.py
rdflib/compat.py
rdflib/events.py
rdflib/exceptions.py
rdflib/graph.py
rdflib/namespace.py
rdflib/parser.py
rdflib/paths.py
rdflib/plugin.py
rdflib/query.py
rdflib/resource.py
rdflib/serializer.py
rdflib/store.py
rdflib/term.py
rdflib/util.py
rdflib/void.py
rdflib/extras/__init__.py
rdflib/extras/cmdlineutils.py
rdflib/extras/describer.py
rdflib/extras/external_graph_libs.py
rdflib/extras/infixowl.py
rdflib/plugins/__init__.py
rdflib/plugins/memory.py
rdflib/plugins/sleepycat.py
rdflib/plugins/parsers/__init__.py
rdflib/plugins/parsers/notation3.py
rdflib/plugins/parsers/nquads.py
rdflib/plugins/parsers/nt.py
rdflib/plugins/parsers/ntriples.py
rdflib/plugins/parsers/rdfxml.py
rdflib/plugins/parsers/trig.py
rdflib/plugins/parsers/trix.py
rdflib/plugins/serializers/__init__.py
rdflib/plugins/serializers/n3.py
rdflib/plugins/serializers/nquads.py
rdflib/plugins/serializers/nt.py
rdflib/plugins/serializers/rdfxml.py
rdflib/plugins/serializers/trig.py
rdflib/plugins/serializers/trix.py
rdflib/plugins/serializers/turtle.py
rdflib/plugins/serializers/xmlwriter.py
rdflib/plugins/sparql/__init__.py
rdflib/plugins/sparql/aggregates.py
rdflib/plugins/sparql/algebra.py
rdflib/plugins/sparql/datatypes.py
rdflib/plugins/sparql/evaluate.py
rdflib/plugins/sparql/evalutils.py
rdflib/plugins/sparql/operators.py
rdflib/plugins/sparql/parser.py
rdflib/plugins/sparql/parserutils.py
rdflib/plugins/sparql/processor.py
rdflib/plugins/sparql/sparql.py
rdflib/plugins/sparql/update.py
rdflib/plugins/sparql/results/__init__.py
rdflib/plugins/sparql/results/csvresults.py
rdflib/plugins/sparql/results/graph.py
rdflib/plugins/sparql/results/jsonresults.py
rdflib/plugins/sparql/results/rdfresults.py
rdflib/plugins/sparql/results/tsvresults.py
rdflib/plugins/sparql/results/txtresults.py
rdflib/plugins/sparql/results/xmlresults.py
rdflib/plugins/stores/__init__.py
rdflib/plugins/stores/auditable.py
rdflib/plugins/stores/concurrent.py
neurdflib-5.0.1.dist-info/LICENSE
neurdflib-5.0.1.dist-info/METADATA
neurdflib-5.0.1.dist-info/WHEEL
neurdflib-5.0.1.dist-info/entry_points.txt
neurdflib-5.0.1.dist-info/top_level.txt
neurdflib-5.0.1.dist-info/RECORD
